toloka/a9s/client/__init__.py
toloka/a9s/client/base/__init__.py
toloka/a9s/client/base/client.py
toloka/a9s/client/base/converter.py
toloka/a9s/client/base/exception.py
toloka/a9s/client/base/types.py
toloka/a9s/client/client/__init__.py
toloka/a9s/client/client/annotation.py
toloka/a9s/client/client/annotation_edit.py
toloka/a9s/client/client/annotation_files.py
toloka/a9s/client/client/annotation_metric.py
toloka/a9s/client/client/batch.py
toloka/a9s/client/client/experimental/__init__.py
toloka/a9s/client/client/experimental/annotation_process/__init__.py
toloka/a9s/client/client/experimental/annotation_process/post_acceptance.py
toloka/a9s/client/client/experimental/annotation_process/quorum.py
toloka/a9s/client/client/experimental/annotation_process/review.py
toloka/a9s/client/client/experimental/annotation_process/sft/__init__.py
toloka/a9s/client/client/experimental/annotation_process/sft/logs.py
toloka/a9s/client/client/experimental/annotation_process/status_workflow.py
toloka/a9s/client/client/experimental/data_manager.py
toloka/a9s/client/client/experimental/ground_truth.py
toloka/a9s/client/client/experimental/quality_management/__init__.py
toloka/a9s/client/client/experimental/quality_management/async_config.py
toloka/a9s/client/client/experimental/quality_management/config.py
toloka/a9s/client/client/experimental/quality_management/reset.py
toloka/a9s/client/client/experimental/quality_management/restriction.py
toloka/a9s/client/client/experimental/quality_management/review_extension_config.py
toloka/a9s/client/client/experts_portal/__init__.py
toloka/a9s/client/client/experts_portal/bonus.py
toloka/a9s/client/client/experts_portal/money_config.py
toloka/a9s/client/client/experts_portal/pipeline/__init__.py
toloka/a9s/client/client/experts_portal/pipeline/config.py
toloka/a9s/client/client/experts_portal/pipeline/instance.py
toloka/a9s/client/client/experts_portal/pipeline/money_config.py
a9s_kit-0.6.5.dist-info/WHEEL
a9s_kit-0.6.5.dist-info/METADATA
a9s_kit-0.6.5.dist-info/RECORD
