Metadata-Version: 2.1
Name: a9s_kit
Summary: Annotation Studio SDK
Requires-Python: >= 3.10
Requires-Dist: toloka-http==0.2.1
Requires-Dist: pydantic>=2.8
Version: 0.6.5
